pyvolumio/__init__.py
pyvolumio/volumio.py
pyvolumio-0.1.5.dist-info/LICENSE
pyvolumio-0.1.5.dist-info/METADATA
pyvolumio-0.1.5.dist-info/WHEEL
pyvolumio-0.1.5.dist-info/top_level.txt
pyvolumio-0.1.5.dist-info/RECORD
