Metadata-Version: 2.1
Name: pyvolumio
Version: 0.1.5
Summary: A python library to control Volumio.
Home-page: https://github.com/OnFreund/PyVolumio
Author: On Freund
Author-email: onfreund@gmail.com
License: MIT
Platform: UNKNOWN
Classifier: License :: OSI Approved :: MIT License
Classifier: Programming Language :: Python
Classifier: Programming Language :: Python :: 3
Classifier: Programming Language :: Python :: 3.7
Classifier: Programming Language :: Python :: Implementation :: CPython
Classifier: Programming Language :: Python :: Implementation :: PyPy
Requires-Python: >=3.7.0
License-File: LICENSE
